whitepaper/__init__.py
whitepaper/__main__.py
whitepaper/cli.py
whitepaper/scanner.py
whitepaper/shell.py
whitepaper/utils.py
whitepaper_scanner_cli-0.1.0.dist-info/METADATA
whitepaper_scanner_cli-0.1.0.dist-info/WHEEL
whitepaper_scanner_cli-0.1.0.dist-info/entry_points.txt
whitepaper_scanner_cli-0.1.0.dist-info/top_level.txt
whitepaper_scanner_cli-0.1.0.dist-info/RECORD
