Metadata-Version: 2.4
Name: whitepaper-scanner-cli
Version: 0.1.0
Summary: Whitepaper - Dataset scanner CLI for analysts and policymakers
Author: Vamsi Rajagiri
Requires-Python: >=3.8
Requires-Dist: pandas>=1.3
Requires-Dist: openpyxl>=3.0
Requires-Dist: rich>=12.0
Requires-Dist: typer>=0.9.0
Requires-Dist: click>=8.0.0
